LICENSE
MANIFEST.in
README.md
setup.py
django_variable_settings.egg-info/PKG-INFO
django_variable_settings.egg-info/SOURCES.txt
django_variable_settings.egg-info/dependency_links.txt
django_variable_settings.egg-info/top_level.txt
variable_settings/__init__.py
variable_settings/admin.py
variable_settings/models.py
variable_settings/management/__init__.py
variable_settings/management/commands/__init__.py
variable_settings/management/commands/variable_settings_initialize.py
variable_settings/migrations/0001_initial.py
variable_settings/migrations/__init__.py
variable_settings/templatetags/__init__.py
variable_settings/templatetags/django_variable_settings.py