Metadata-Version: 1.1
Name: django-variable-settings
Version: 0.0.1
Summary: A Django app to have editable key-value namespaced settings.
Home-page: https://github.com/jperelli/django-variable-settings
Author: Julian Perelli
Author-email: jperelli@gmail.com
License: MIT License
Platform: UNKNOWN
Classifier: Environment :: Web Environment
Classifier: Framework :: Django
Classifier: Framework :: Django :: 1.11
Classifier: Intended Audience :: Developers
Classifier: License :: OSI Approved :: MIT License
Classifier: Operating System :: OS Independent
Classifier: Programming Language :: Python
Classifier: Programming Language :: Python :: 2.7
Classifier: Topic :: Internet :: WWW/HTTP
Classifier: Topic :: Internet :: WWW/HTTP :: Dynamic Content
